devopsX/__init__.py
devopsX/abstractdevops.py
devopsX/backlog.py
devopsX/factories.py
devopsX/identity.py
devopsX/interaction.py
devopsX/project.py
devopsX/status.py
devopsX/team.py
devopsX/teammember.py
devopsX/workitem.py
devopsX/workitemtype.py
devopsX-0.0.16.dist-info/METADATA
devopsX-0.0.16.dist-info/WHEEL
devopsX-0.0.16.dist-info/top_level.txt
devopsX-0.0.16.dist-info/RECORD
