Metadata-Version: 2.1
Name: devopsX
Version: 0.0.16
Summary: DevOps é um produto da Microsoft que fornece controle de versão, relatórios, gerenciamento de requisitos, gerenciamento de projetos, compilações automatizadas, gerenciamento de laboratório, recursos de gerenciamento de testes e versões.
Home-page: https://gitlab.com/integration_seon/libs/application/tfs
Author: Paulo Sérgio dos Santos Júnior
Author-email: paulossjunior@gmail.com
Classifier: Programming Language :: Python :: 3
Classifier: License :: OSI Approved :: MIT License
Classifier: Operating System :: OS Independent
Requires-Dist: azure-devops
Requires-Dist: requestx
Requires-Dist: factory-boy
